oeva/__init__.py
oeva/config.py
oeva/eva.py
oeva/system_instructions.py
oeva/views.py
oeva/config/settings.yaml
oeva/tools/__init__.py
oeva/tools/analyze_project.py
oeva/tools/clean_project.py
oeva/tools/create_project.py
oeva/tools/discover_projects.py
oeva/tools/open_project.py
oeva/tools/release_project.py
oeva/tools/tool_handler.py
oeva-1.0.10.dist-info/METADATA
oeva-1.0.10.dist-info/WHEEL
oeva-1.0.10.dist-info/entry_points.txt
oeva-1.0.10.dist-info/top_level.txt
oeva-1.0.10.dist-info/RECORD
