Metadata-Version: 2.2
Name: oeva
Version: 1.0.10
Summary: Eva - A friendly AI assistant for managing your projects
Author-email: Kareem Elbahrawy <kareem.elbahrawy@gmail.com>
Requires-Python: >=3.8
Requires-Dist: openai>=1.0.0
Requires-Dist: python-dotenv>=0.19.0
Requires-Dist: pydantic>=2.0.0
Requires-Dist: rich>=10.0.0
Requires-Dist: typer>=0.9.0
